pytoony/__init__.py
pytoony/cli.py
pytoony/converter.py
pytoony/toon.py
pytoony-0.1.2.dist-info/licenses/LICENSE
tests/__init__.py
tests/test_cli.py
tests/test_converter.py
pytoony-0.1.2.dist-info/METADATA
pytoony-0.1.2.dist-info/WHEEL
pytoony-0.1.2.dist-info/entry_points.txt
pytoony-0.1.2.dist-info/top_level.txt
pytoony-0.1.2.dist-info/RECORD
